{
    "agricultural": [
        "agriculture",
        "agricultural"
    ],
    "sip": [
        "sip"
    ],
    "retirement": [
        "retirement",
        "retire"
    ],
    "business": [
        "business",
        "start",
        "market",
        "startup",
        "company",
        "venture",
        "bissuness",
        "buisness"
    ],
    "army": [
        "army"
    ],
    "charity": [
        "charity",
        "help",
        "donate",
        "give",
        "needy",
        "poor",
        "welfare",
        "helping",
        "ngo",
        "orphanage",
        "chairity",
        "donation",
        "needed",
        "charitable",
        "cherety",
        "cherity",
        "contribute",
        "donating",
        "donet",
        "maid",
        "ngo's",
        "orphan",
        "philanthropic",
        "trust",
        "underprivileged",
        "upliftment"
    ],
    "children": [
        "child",
        "daughter",
        "kid",
        "daughter's",
        "child's",
        "son",
        "chidren",
        "chil's",
        "children's"
    ],
    "education": [
        "education",
        "school",
        "student",
        "educational",
        "learning",
        "study",
        "educating",
        "educationaly",
        "educationally",
        "geotechnical",
        "knowledge",
        "laboratory",
        "learn",
        "library"
    ],
    "environment": [
        "environemnt",
        "natural",
        "trees"
    ],
    "bonds": [
        "bond",
        "bonds"
    ],
    "equity": [
        "return",
        "returns",
        "stock",
        "share",
        "equity",
        "risk",
        "multicap",
        "portfolio",
        "reliance",
        "risk-free",
        "script",
        "tc",
        "risk",
        "tcs"
    ],
    "buy": [
        "buy",
        "buying",
        "purchase",
        "purchasing",
        "buing"
    ],
    "tax": [
        "tax",
        "taxes"
    ],
    "marriage": [
        "marriage"
    ],
    "leisure": [
        "shopping",
        "gift",
        "shop",
        "liquor",
        "enjoy",
        "enjoyed",
        "enjoying",
        "enjoyment",
        "entertainment",
        "fun",
        "food"
    ],
    "luxury": [
        "luxury",
        "luxuries",
        "luxurious",
        "luxury!"
    ],
    "medical expenses": [
        "medical",
        "hospital"
    ],
    "spend": [
        "spend",
        "spending",
        "personal use",
        "personal things",
        "expense",
        "expenses",
        "spent",
        "rent",
        "expenditure",
        "item",
        "emi",
        "expence",
        "expenditrue",
        "fee",
        "sponsor"
    ],
    "family": [
        "family",
        "parent",
        "family's",
        "friend",
        "wife",
        "husband",
        "brother",
        "famiely",
        "girl",
        "groom",
        "in-law",
        "relative"
    ],
    "fixed deposits": [
        "fixed deposit",
        "fixed disposite",
        "fixed deposite",
        "deposit",
        "bank",
        "fixed",
        "regular return",
        "regular income",
        "fd",
        "f.d",
        "deposite",
        "fds",
        "deposites",
        "diposite"
    ],
    "gadgets": [
        "gadgets"
    ],
    "silver": [
        "silver"
    ],
    "gold": [
        "gold",
        "coin",
        "safe",
        "jewellery",
        "jewelery",
        "jwellery"
    ],
    "debentures": [
        "debentures",
        "debenture"
    ],
    "laboratory": [
        "laboratory"
    ],
    "house": [
        "house",
        "home",
        "flat",
        "build",
        "housing",
        "bungalow",
        "duplex",
        "hom",
        "house"
    ],
    "income": [
        "asset",
        "interest",
        "earn",
        "earning"
    ],
    "insurance": [
        "insurance",
        "policy",
        "mediclaim"
    ],
    "cryptocurrency": [
        "cryptocurrencys",
        "cryptocurrency",
        "cryptocurrencies",
        "crypto"
    ],
    "pets": [
        "dogs",
        "cow",
        "cats"
    ],
    "e-gold": [
        "e-gold"
    ],
    "investment": [
        "invest",
        "investment",
        "secure",
        "investing",
        "security",
        "invested",
        "gain",
        "health",
        "capital",
        "grow",
        "growth",
        "profit",
        "provident",
        "intvestin",
        "inves",
        "investe",
        "reinvest",
        "roi"
    ],
    "loan": [
        "loan",
        "pay",
        "debt",
        "due",
        "loans",
        "liability",
        "liabilities",
        "repay",
        "paying",
        "payment",
        "debenture"
    ],
    "lottery": [
        "lottery",
        "won",
        "win",
        "free"
    ],
    "money": [
        "money",
        "amount",
        "cash",
        "liquid",
        "amt",
        "penny"
    ],
    "secure future": [
        "future"
    ],
    "mutual funds": [
        "mutual fund",
        "mutual funds",
        "mutual-funds",
        "mutual-fund",
        "mutual",
        "fund",
        "m.f",
        "mf",
        "m.f.",
        "mf."
    ],
    "pension fund": [
        "pension funds",
        "pension fund",
        "pension"
    ],
    "post office investment": [
        "post"
    ],
    "ppf": [
        "ppf",
        "govt fund",
        "govt funds"
    ],
    "emergency": [
        "emergency",
        "embergency"
    ],
    "property": [
        "real estate",
        "property",
        "land",
        "estate",
        "real",
        "bhk",
        "plot",
        "building",
        "construct",
        "residential"
    ],
    "society": [
        "society",
        "social",
        "community",
        "country"
    ],
    "saving": [
        "save",
        "income",
        "saving"
    ],
    "travel": [
        "tour",
        "travel",
        "world",
        "vacation",
        "travelling",
        "foreign",
        "trip",
        "abroad",
        "international",
        "visit",
        "visiting",
        "holiday",
        "travell",
        "outing"
    ],
    "vehicles": [
        "car",
        "vehicle",
        "audi",
        "bike",
        "bmw",
        "enfield",
        "suv",
        "vehical",
        "wheeler"
    ]
}